yashpy/__init__.py
yashpy-1.0.dist-info/METADATA
yashpy-1.0.dist-info/WHEEL
yashpy-1.0.dist-info/licence.txt
yashpy-1.0.dist-info/top_level.txt
yashpy-1.0.dist-info/RECORD
