Metadata-Version: 2.1
Name: yashpy
Version: 1.0
Summary: this is mathematics perps lybrary
Author: yshirsath466@gmail.com
License-File: licence.txt
